cbfpy/__init__.py
cbfpy/cbfs/__init__.py
cbfpy/cbfs/cbf.py
cbfpy/cbfs/clf_cbf.py
cbfpy/config/__init__.py
cbfpy/config/cbf_config.py
cbfpy/config/clf_cbf_config.py
cbfpy/envs/__init__.py
cbfpy/envs/arm_envs.py
cbfpy/envs/base_env.py
cbfpy/envs/car_env.py
cbfpy/envs/drone_env.py
cbfpy/envs/point_robot_envs.py
cbfpy/examples/__init__.py
cbfpy/examples/adaptive_cruise_control_demo.py
cbfpy/examples/drone_demo.py
cbfpy/examples/joint_limits_demo.py
cbfpy/examples/point_robot_demo.py
cbfpy/examples/point_robot_obstacle_demo.py
cbfpy/temp/test_import.py
cbfpy/utils/__init__.py
cbfpy/utils/general_utils.py
cbfpy/utils/jax_utils.py
cbfpy/utils/math_utils.py
cbfpy/utils/visualization.py
test/__init__.py
test/test_speed.py
test/test_utils.py
cbfpy-0.0.1.dist-info/LICENSE
cbfpy-0.0.1.dist-info/METADATA
cbfpy-0.0.1.dist-info/WHEEL
cbfpy-0.0.1.dist-info/top_level.txt
cbfpy-0.0.1.dist-info/RECORD
