Metadata-Version: 2.1
Name: cbfpy
Version: 0.0.1
Summary: Control Barrier Functions in Python
Author-email: Daniel Morton <danielpmorton@gmail.com>
Project-URL: Documentation, https://danielpmorton.github.io/cbfpy/
Project-URL: Repository, https://github.com/danielpmorton/cbfpy/
Keywords: control,barrier,function,CBF,Jax
Classifier: Programming Language :: Python :: 3
Classifier: License :: OSI Approved :: MIT License
Classifier: Operating System :: OS Independent
License-File: LICENSE
Requires-Dist: numpy<2
Requires-Dist: jax
Requires-Dist: jaxlib
Requires-Dist: qpax
Provides-Extra: examples
Requires-Dist: pybullet; extra == "examples"
Requires-Dist: pygame; extra == "examples"
Requires-Dist: wheel; extra == "examples"
Requires-Dist: matplotlib; extra == "examples"
Provides-Extra: dev
Requires-Dist: mkdocs-material; extra == "dev"
Requires-Dist: mkdocstrings[python]; extra == "dev"
Requires-Dist: pylint; extra == "dev"
Requires-Dist: black; extra == "dev"
Provides-Extra: all
Requires-Dist: pylint; extra == "all"
Requires-Dist: black; extra == "all"
Requires-Dist: pybullet; extra == "all"
Requires-Dist: pygame; extra == "all"
Requires-Dist: mkdocs-material; extra == "all"
Requires-Dist: mkdocstrings[python]; extra == "all"
